mlcrawler/__init__.py
mlcrawler/api.py
mlcrawler/cache.py
mlcrawler/cli.py
mlcrawler/config.py
mlcrawler/crawl.py
mlcrawler/extract.py
mlcrawler/fetch.py
mlcrawler/links.py
mlcrawler/output.py
mlcrawler/page.py
mlcrawler/robots.py
mlcrawler/sitemap.py
mlcrawler-0.2.0.dist-info/METADATA
mlcrawler-0.2.0.dist-info/WHEEL
mlcrawler-0.2.0.dist-info/entry_points.txt
mlcrawler-0.2.0.dist-info/RECORD
