Metadata-Version: 2.4
Name: mlcrawler
Version: 0.2.0
Summary: A thin, configurable Python crawler/scraper with sitemap and seed-url modes
Requires-Python: >=3.11
Requires-Dist: beautifulsoup4>=4.13.4
Requires-Dist: dynaconf>=3.2.11
Requires-Dist: httpx>=0.27.0
Requires-Dist: lxml>=5.3.0
Requires-Dist: markdownify>=1.2.0
Requires-Dist: python-slugify>=8.0.4
Requires-Dist: trafilatura>=1.12.2
Requires-Dist: typer[all]>=0.15.0
